{
  "rule": "crystal_dendritic",
  "size": 144,
  "seed": 1001,
  "dt": 0.025,
  "init": "crystal_seed",
  "params": {
    "Undercooling": 0.5,
    "Diffusion": 0.02,
    "Anisotropy strength": 2.5,
    "Shape": 3
  },
  "checkpoints": [
    25,
    100,
    250
  ],
  "snapshots": [
    {
      "step": 25,
      "hash": "648665db109244e25639f2700c755cc26aa03b6275964f93a0e9bd72d5254dd4",
      "stats": {
        "shape": [
          144,
          144,
          144,
          4
        ],
        "channels": [
          {
            "mean": 8.663673361297697e-05,
            "std": 0.008275866508483887,
            "min": 0.0,
            "max": 0.9999905228614807,
            "alive": 1738,
            "nonfinite": 0
          },
          {
            "mean": 0.24980686604976654,
            "std": 0.002847729716449976,
            "min": 7.609190106450114e-06,
            "max": 0.2547759711742401,
            "alive": 2985984,
            "nonfinite": 0
          },
          {
            "mean": 0.0,
            "std": 0.0,
            "min": 0.0,
            "max": 0.0,
            "alive": 0,
            "nonfinite": 0
          },
          {
            "mean": 0.0,
            "std": 0.0,
            "min": 0.0,
            "max": 0.0,
            "alive": 0,
            "nonfinite": 0
          }
        ]
      }
    },
    {
      "step": 100,
      "hash": "1849d9717190401e23e426ee02e9da4a582bd0a081b46997fd0bea1ebcaa2f8c",
      "stats": {
        "shape": [
          144,
          144,
          144,
          4
        ],
        "channels": [
          {
            "mean": 0.0004480668867472559,
            "std": 0.014470458030700684,
            "min": 0.0,
            "max": 0.9999650716781616,
            "alive": 8155,
            "nonfinite": 0
          },
          {
            "mean": 0.24915175139904022,
            "std": 0.007095379289239645,
            "min": -0.020403532311320305,
            "max": 0.2544957101345062,
            "alive": 2985984,
            "nonfinite": 0
          },
          {
            "mean": 0.0,
            "std": 0.0,
            "min": 0.0,
            "max": 0.0,
            "alive": 0,
            "nonfinite": 0
          },
          {
            "mean": 1.4214596149031422e-06,
            "std": 0.00016158683865796775,
            "min": 0.0,
            "max": 0.04214387759566307,
            "alive": 288,
            "nonfinite": 0
          }
        ]
      }
    },
    {
      "step": 250,
      "hash": "b6d312698ee00308f32483f2d61f77c09f9cc7048f20eadc38322ed4e9d031cb",
      "stats": {
        "shape": [
          144,
          144,
          144,
          4
        ],
        "channels": [
          {
            "mean": 0.00429557217285037,
            "std": 0.04344325140118599,
            "min": 0.0,
            "max": 0.9999734163284302,
            "alive": 49551,
            "nonfinite": 0
          },
          {
            "mean": 0.2463408261537552,
            "std": 0.022244084626436234,
            "min": -0.06702061742544174,
            "max": 0.254102885723114,
            "alive": 2985983,
            "nonfinite": 0
          },
          {
            "mean": 7.502090011257678e-05,
            "std": 0.00707183126360178,
            "min": 0.0,
            "max": 0.666700005531311,
            "alive": 336,
            "nonfinite": 0
          },
          {
            "mean": 2.6564955987851135e-05,
            "std": 0.0006629917188547552,
            "min": 0.0,
            "max": 0.060897983610630035,
            "alive": 6425,
            "nonfinite": 0
          }
        ]
      }
    }
  ],
  "blessed_at": "2026-05-26T22:56:39+00:00",
  "note": "initial bootstrap (engine state at d9e8968 + Bug J fix)"
}