{
  "rule": "crystal_hopper",
  "size": 48,
  "seed": 1001,
  "dt": 0.01,
  "init": "crystal_seed",
  "params": {
    "Undercooling": 0.45,
    "Diffusion": 0.06,
    "Anisotropy strength": 5.0,
    "Shape": 5
  },
  "checkpoints": [
    25,
    100,
    250
  ],
  "snapshots": [
    {
      "step": 25,
      "hash": "4b2c691c2d76a4c280617bfafb405b54de2498d80c6b8d3edbf08003e07c7468",
      "stats": {
        "shape": [
          48,
          48,
          48,
          4
        ],
        "channels": [
          {
            "mean": 0.00035780819598585367,
            "std": 0.017878597602248192,
            "min": 0.0,
            "max": 0.9999877214431763,
            "alive": 404,
            "nonfinite": 0
          },
          {
            "mean": 0.24983201920986176,
            "std": 0.0049938028678298,
            "min": -0.006009305361658335,
            "max": 0.25469347834587097,
            "alive": 110592,
            "nonfinite": 0
          },
          {
            "mean": 0.0,
            "std": 0.0,
            "min": 0.0,
            "max": 0.0,
            "alive": 0,
            "nonfinite": 0
          },
          {
            "mean": 1.2265489885976422e-06,
            "std": 0.0003127164382021874,
            "min": 0.0,
            "max": 0.09624107927083969,
            "alive": 2,
            "nonfinite": 0
          }
        ]
      }
    },
    {
      "step": 100,
      "hash": "6dd34950291ef73fd44f0a65ae8d3fdb4ebfb55dee3c616532fbb40c63656bf7",
      "stats": {
        "shape": [
          48,
          48,
          48,
          4
        ],
        "channels": [
          {
            "mean": 0.0008946637972258031,
            "std": 0.023141205310821533,
            "min": 0.0,
            "max": 0.9999898076057434,
            "alive": 1252,
            "nonfinite": 0
          },
          {
            "mean": 0.24936825037002563,
            "std": 0.008850864134728909,
            "min": -0.024279547855257988,
            "max": 0.2545914351940155,
            "alive": 110592,
            "nonfinite": 0
          },
          {
            "mean": 0.0,
            "std": 0.0,
            "min": 0.0,
            "max": 0.0,
            "alive": 0,
            "nonfinite": 0
          },
          {
            "mean": 1.5202275790215936e-05,
            "std": 0.0010675902012735605,
            "min": 0.0,
            "max": 0.14216618239879608,
            "alive": 35,
            "nonfinite": 0
          }
        ]
      }
    },
    {
      "step": 250,
      "hash": "443d924216f2d3c02b6d7af415f5ccbd3dea6ca4998dabc1f68c5a5168cf2533",
      "stats": {
        "shape": [
          48,
          48,
          48,
          4
        ],
        "channels": [
          {
            "mean": 0.006860950030386448,
            "std": 0.05638827756047249,
            "min": 0.0,
            "max": 0.9999914765357971,
            "alive": 5003,
            "nonfinite": 0
          },
          {
            "mean": 0.2459983080625534,
            "std": 0.027103479951620102,
            "min": -0.04254647344350815,
            "max": 0.2543945610523224,
            "alive": 110592,
            "nonfinite": 0
          },
          {
            "mean": 0.0,
            "std": 0.0,
            "min": 0.0,
            "max": 0.0,
            "alive": 0,
            "nonfinite": 0
          },
          {
            "mean": 0.0001283600286114961,
            "std": 0.0028508109971880913,
            "min": 0.0,
            "max": 0.16184338927268982,
            "alive": 396,
            "nonfinite": 0
          }
        ]
      }
    }
  ],
  "blessed_at": "2026-05-26T22:56:39+00:00",
  "note": "initial bootstrap (engine state at d9e8968 + Bug J fix)"
}